PyAppWrite/__init__.py
PyAppWrite/client.py
PyAppWrite/exception.py
PyAppWrite/id.py
PyAppWrite/input_file.py
PyAppWrite/permission.py
PyAppWrite/query.py
PyAppWrite/role.py
PyAppWrite/service.py
PyAppWrite/encoders/__init__.py
PyAppWrite/encoders/value_class_encoder.py
PyAppWrite/enums/__init__.py
PyAppWrite/enums/authentication_factor.py
PyAppWrite/enums/authenticator_type.py
PyAppWrite/enums/browser.py
PyAppWrite/enums/compression.py
PyAppWrite/enums/credit_card.py
PyAppWrite/enums/execution_method.py
PyAppWrite/enums/flag.py
PyAppWrite/enums/image_format.py
PyAppWrite/enums/image_gravity.py
PyAppWrite/enums/index_type.py
PyAppWrite/enums/messaging_provider_type.py
PyAppWrite/enums/name.py
PyAppWrite/enums/o_auth_provider.py
PyAppWrite/enums/password_hash.py
PyAppWrite/enums/relation_mutate.py
PyAppWrite/enums/relationship_type.py
PyAppWrite/enums/runtime.py
PyAppWrite/enums/smtp_encryption.py
PyAppWrite/services/__init__.py
PyAppWrite/services/account.py
PyAppWrite/services/avatars.py
PyAppWrite/services/databases.py
PyAppWrite/services/functions.py
PyAppWrite/services/graphql.py
PyAppWrite/services/health.py
PyAppWrite/services/locale.py
PyAppWrite/services/messaging.py
PyAppWrite/services/storage.py
PyAppWrite/services/teams.py
PyAppWrite/services/users.py
PyAppWrite-1.0.0.2.dist-info/LICENSE
PyAppWrite-1.0.0.2.dist-info/METADATA
PyAppWrite-1.0.0.2.dist-info/WHEEL
PyAppWrite-1.0.0.2.dist-info/top_level.txt
PyAppWrite-1.0.0.2.dist-info/RECORD
